django_template_integrator/__init__.py
django_template_integrator/cli.py
django_template_integrator/core.py
django_template_integrator/utils.py
django_template_integrator-1.0.1.dist-info/METADATA
django_template_integrator-1.0.1.dist-info/WHEEL
django_template_integrator-1.0.1.dist-info/top_level.txt
django_template_integrator-1.0.1.dist-info/RECORD
