Metadata-Version: 2.4
Name: django-template-integrator
Version: 1.0.1
Summary: Easily integrate any HTML template into your Django project
Author-email: Daniyal Akhtar <your@email.com>
License: MIT
Requires-Python: >=3.8
Requires-Dist: beautifulsoup4>=4.12.0
